hxss/__init__.py
hxss/responsibility/__init__.py
hxss/responsibility/link.py
hxss/responsibility/request.py
hxss/responsibility/response.py
hxss/responsibility/smart_self_static_factory.py
test/__init__.py
test/responsibility/__init__.py
test/responsibility/test_chain.py
hxss.responsibility-0.1.1.dist-info/LICENSE
hxss.responsibility-0.1.1.dist-info/METADATA
hxss.responsibility-0.1.1.dist-info/WHEEL
hxss.responsibility-0.1.1.dist-info/top_level.txt
hxss.responsibility-0.1.1.dist-info/RECORD
