Metadata-Version: 2.1
Name: hxss.responsibility
Version: 0.1.1
Summary: Simple implementation of `chain of responsibilities` pattern
Home-page: https://gitlab.com/hxss-python/hxss.responsibility
Author: hxss
Author-email: hxss@ya.ru
License: UNKNOWN
Keywords: chain,responsibility,pattern,coalescing
Platform: UNKNOWN
Classifier: Programming Language :: Python :: 3
Classifier: License :: OSI Approved :: MIT License
Classifier: Topic :: Software Development :: Libraries :: Python Modules
